{"code":0,"data":{"A":[{"id":484647,"name":"\u963f\u62c9\u5584\u76df","type":2,"path":"1529","parentId":468973,"sort":0,"initial":"A"},{"id":455742,"name":"\u978d\u5c71","type":2,"path":"2103","parentId":451186,"sort":0,"initial":"A"},{"id":87753,"name":"\u5b89\u5e86","type":2,"path":"3408","parentId":81714,"sort":0,"initial":"A"},{"id":249675,"name":"\u5b89\u9633","type":2,"path":"4105","parentId":237641,"sort":0,"initial":"A"},{"id":702109,"name":"\u963f\u575d\u5dde","type":2,"path":"5132","parentId":650698,"sort":0,"initial":"A"},{"id":158292,"name":"\u5b89\u987a","type":2,"path":"5204","parentId":152964,"sort":0,"initial":"A"},{"id":722694,"name":"\u963f\u91cc","type":2,"path":"5425","parentId":716798,"sort":0,"initial":"A"},{"id":640315,"name":"\u5b89\u5eb7","type":2,"path":"6109","parentId":613964,"sort":0,"initial":"A"},{"id":728067,"name":"\u963f\u514b\u82cf","type":2,"path":"6529","parentId":723476,"sort":0,"initial":"A"},{"id":737663,"name":"\u963f\u52d2\u6cf0","type":2,"path":"6543","parentId":723476,"sort":0,"initial":"A"}],"B":[{"id":74874,"name":"\u5317\u4eac","type":2,"path":"1101","parentId":74873,"sort":0,"initial":"B"},{"id":208054,"name":"\u4fdd\u5b9a","type":2,"path":"1306","parentId":182754,"sort":0,"initial":"B"},{"id":470335,"name":"\u5305\u5934","type":2,"path":"1502","parentId":468973,"sort":0,"initial":"B"},{"id":479482,"name":"\u5df4\u5f66\u6dd6\u5c14","type":2,"path":"1508","parentId":468973,"sort":0,"initial":"B"},{"id":458067,"name":"\u672c\u6eaa","type":2,"path":"2105","parentId":451186,"sort":0,"initial":"B"},{"id":398841,"name":"\u767d\u5c71","type":2,"path":"2206","parentId":391143,"sort":0,"initial":"B"},{"id":401038,"name":"\u767d\u57ce","type":2,"path":"2208","parentId":391143,"sort":0,"initial":"B"},{"id":84117,"name":"\u868c\u57e0","type":2,"path":"3403","parentId":81714,"sort":0,"initial":"B"},{"id":570636,"name":"\u6ee8\u5dde","type":2,"path":"3716","parentId":493130,"sort":0,"initial":"B"},{"id":141755,"name":"\u5317\u6d77","type":2,"path":"4505","parentId":135425,"sort":0,"initial":"B"},{"id":146522,"name":"\u767e\u8272","type":2,"path":"4510","parentId":135425,"sort":0,"initial":"B"},{"id":696157,"name":"\u5df4\u4e2d","type":2,"path":"5119","parentId":650698,"sort":0,"initial":"B"},{"id":165461,"name":"\u6bd5\u8282","type":2,"path":"5224","parentId":152964,"sort":0,"initial":"B"},{"id":743265,"name":"\u4fdd\u5c71","type":2,"path":"5305","parentId":739032,"sort":0,"initial":"B"},{"id":618522,"name":"\u5b9d\u9e21","type":2,"path":"6103","parentId":613964,"sort":0,"initial":"B"},{"id":57384,"name":"\u767d\u94f6","type":2,"path":"6204","parentId":55845,"sort":0,"initial":"B"},{"id":726556,"name":"\u535a\u5c14\u5854\u62c9\u8499\u53e4\u81ea\u6cbb\u5dde","type":2,"path":"6527","parentId":723476,"sort":0,"initial":"B"},{"id":727104,"name":"\u5df4\u97f3\u90ed\u695e\u8499\u53e4\u81ea\u6cbb\u5dde","type":2,"path":"6528","parentId":723476,"sort":0,"initial":"B"}],"C":[{"id":219677,"name":"\u627f\u5fb7","type":2,"path":"1308","parentId":182754,"sort":0,"initial":"C"},{"id":222616,"name":"\u6ca7\u5dde","type":2,"path":"1309","parentId":182754,"sort":0,"initial":"C"},{"id":587546,"name":"\u957f\u6cbb","type":2,"path":"1404","parentId":582414,"sort":0,"initial":"C"},{"id":471644,"name":"\u8d64\u5cf0","type":2,"path":"1504","parentId":468973,"sort":0,"initial":"C"},{"id":465783,"name":"\u671d\u9633","type":2,"path":"2113","parentId":451186,"sort":0,"initial":"C"},{"id":391144,"name":"\u957f\u6625","type":2,"path":"2201","parentId":391143,"sort":0,"initial":"C"},{"id":409936,"name":"\u5e38\u5dde","type":2,"path":"3204","parentId":403889,"sort":0,"initial":"C"},{"id":91164,"name":"\u6ec1\u5dde","type":2,"path":"3411","parentId":81714,"sort":0,"initial":"C"},{"id":99394,"name":"\u5de2\u6e56","type":2,"path":"3414","parentId":81714,"sort":0,"initial":"C"},{"id":105719,"name":"\u6c60\u5dde","type":2,"path":"3417","parentId":81714,"sort":0,"initial":"C"},{"id":339657,"name":"\u957f\u6c99","type":2,"path":"4301","parentId":339656,"sort":0,"initial":"C"},{"id":361534,"name":"\u5e38\u5fb7","type":2,"path":"4307","parentId":339656,"sort":0,"initial":"C"},{"id":371667,"name":"\u90f4\u5dde","type":2,"path":"4310","parentId":339656,"sort":0,"initial":"C"},{"id":131531,"name":"\u6f6e\u5dde","type":2,"path":"4451","parentId":107712,"sort":0,"initial":"C"},{"id":152035,"name":"\u5d07\u5de6","type":2,"path":"4514","parentId":135425,"sort":0,"initial":"C"},{"id":754686,"name":"\u91cd\u5e86","type":2,"path":"5001","parentId":754685,"sort":0,"initial":"C"},{"id":650699,"name":"\u6210\u90fd","type":2,"path":"5101","parentId":650698,"sort":0,"initial":"C"},{"id":748416,"name":"\u695a\u96c4\u5dde","type":2,"path":"5323","parentId":739032,"sort":0,"initial":"C"},{"id":717141,"name":"\u660c\u90fd","type":2,"path":"5421","parentId":716798,"sort":0,"initial":"C"},{"id":725030,"name":"\u660c\u5409\u5dde","type":2,"path":"6523","parentId":723476,"sort":0,"initial":"C"}],"D":[{"id":584021,"name":"\u5927\u540c","type":2,"path":"1402","parentId":582414,"sort":0,"initial":"D"},{"id":454017,"name":"\u5927\u8fde","type":2,"path":"2102","parentId":451186,"sort":0,"initial":"D"},{"id":458658,"name":"\u4e39\u4e1c","type":2,"path":"2106","parentId":451186,"sort":0,"initial":"D"},{"id":299119,"name":"\u5927\u5e86","type":2,"path":"2306","parentId":291426,"sort":0,"initial":"D"},{"id":307447,"name":"\u5927\u5174\u5b89\u5cad","type":2,"path":"2327","parentId":291426,"sort":0,"initial":"D"},{"id":511483,"name":"\u4e1c\u8425","type":2,"path":"3705","parentId":493130,"sort":0,"initial":"D"},{"id":555512,"name":"\u5fb7\u5dde","type":2,"path":"3714","parentId":493130,"sort":0,"initial":"D"},{"id":130588,"name":"\u4e1c\u839e","type":2,"path":"4419","parentId":107712,"sort":0,"initial":"D"},{"id":659022,"name":"\u5fb7\u9633","type":2,"path":"5106","parentId":650698,"sort":0,"initial":"D"},{"id":691410,"name":"\u8fbe\u5dde","type":2,"path":"5117","parentId":650698,"sort":0,"initial":"D"},{"id":752477,"name":"\u5927\u7406\u5dde","type":2,"path":"5329","parentId":739032,"sort":0,"initial":"D"},{"id":753733,"name":"\u5fb7\u5b8f\u5dde","type":2,"path":"5331","parentId":739032,"sort":0,"initial":"D"},{"id":754465,"name":"\u8fea\u5e86\u5dde","type":2,"path":"5334","parentId":739032,"sort":0,"initial":"D"},{"id":67206,"name":"\u5b9a\u897f","type":2,"path":"6211","parentId":55845,"sort":0,"initial":"D"}],"E":[{"id":476707,"name":"\u9102\u5c14\u591a\u65af","type":2,"path":"1506","parentId":468973,"sort":0,"initial":"E"},{"id":319186,"name":"\u9102\u5dde","type":2,"path":"4207","parentId":307715,"sort":0,"initial":"E"},{"id":334770,"name":"\u6069\u65bd\u5dde","type":2,"path":"4228","parentId":307715,"sort":0,"initial":"E"}],"F":[{"id":457000,"name":"\u629a\u987a","type":2,"path":"2104","parentId":451186,"sort":0,"initial":"F"},{"id":462003,"name":"\u961c\u65b0","type":2,"path":"2109","parentId":451186,"sort":0,"initial":"F"},{"id":93856,"name":"\u961c\u9633","type":2,"path":"3412","parentId":81714,"sort":0,"initial":"F"},{"id":3,"name":"\u798f\u5dde","type":2,"path":"3501","parentId":2,"sort":0,"initial":"F"},{"id":445939,"name":"\u629a\u5dde","type":2,"path":"3610","parentId":428836,"sort":0,"initial":"F"},{"id":114247,"name":"\u4f5b\u5c71","type":2,"path":"4406","parentId":107712,"sort":0,"initial":"F"},{"id":142227,"name":"\u9632\u57ce\u6e2f","type":2,"path":"4506","parentId":135425,"sort":0,"initial":"F"}],"G":[{"id":435938,"name":"\u8d63\u5dde","type":2,"path":"3607","parentId":428836,"sort":0,"initial":"G"},{"id":107713,"name":"\u5e7f\u5dde","type":2,"path":"4401","parentId":107712,"sort":0,"initial":"G"},{"id":138674,"name":"\u6842\u6797","type":2,"path":"4503","parentId":135425,"sort":0,"initial":"G"},{"id":143725,"name":"\u8d35\u6e2f","type":2,"path":"4508","parentId":135425,"sort":0,"initial":"G"},{"id":665565,"name":"\u5e7f\u5143","type":2,"path":"5108","parentId":650698,"sort":0,"initial":"G"},{"id":688272,"name":"\u5e7f\u5b89","type":2,"path":"5116","parentId":650698,"sort":0,"initial":"G"},{"id":703762,"name":"\u7518\u5b5c\u85cf\u65cf\u81ea\u6cbb\u5dde","type":2,"path":"5133","parentId":650698,"sort":0,"initial":"G"},{"id":152965,"name":"\u8d35\u9633","type":2,"path":"5201","parentId":152964,"sort":0,"initial":"G"},{"id":74067,"name":"\u7518\u5357\u5dde","type":2,"path":"6230","parentId":55845,"sort":0,"initial":"G"},{"id":492141,"name":"\u679c\u6d1b\u5dde","type":2,"path":"6326","parentId":488119,"sort":0,"initial":"G"},{"id":486564,"name":"\u56fa\u539f","type":2,"path":"6404","parentId":484915,"sort":0,"initial":"G"}],"H":[{"id":196500,"name":"\u90af\u90f8","type":2,"path":"1304","parentId":182754,"sort":0,"initial":"H"},{"id":232454,"name":"\u8861\u6c34","type":2,"path":"1311","parentId":182754,"sort":0,"initial":"H"},{"id":468974,"name":"\u547c\u548c\u6d69\u7279","type":2,"path":"1501","parentId":468973,"sort":0,"initial":"H"},{"id":477692,"name":"\u547c\u4f26\u8d1d\u5c14","type":2,"path":"1507","parentId":468973,"sort":0,"initial":"H"},{"id":467520,"name":"\u846b\u82a6\u5c9b","type":2,"path":"2114","parentId":451186,"sort":0,"initial":"H"},{"id":291427,"name":"\u54c8\u5c14\u6ee8","type":2,"path":"2301","parentId":291426,"sort":0,"initial":"H"},{"id":297701,"name":"\u9e64\u5c97","type":2,"path":"2304","parentId":291426,"sort":0,"initial":"H"},{"id":304374,"name":"\u9ed1\u6cb3","type":2,"path":"2311","parentId":291426,"sort":0,"initial":"H"},{"id":417852,"name":"\u6dee\u5b89","type":2,"path":"3208","parentId":403889,"sort":0,"initial":"H"},{"id":18048,"name":"\u676d\u5dde","type":2,"path":"3301","parentId":18047,"sort":0,"initial":"H"},{"id":33214,"name":"\u6e56\u5dde","type":2,"path":"3305","parentId":18047,"sort":0,"initial":"H"},{"id":81715,"name":"\u5408\u80a5","type":2,"path":"3401","parentId":81714,"sort":0,"initial":"H"},{"id":85357,"name":"\u6dee\u5357","type":2,"path":"3404","parentId":81714,"sort":0,"initial":"H"},{"id":86640,"name":"\u6dee\u5317","type":2,"path":"3406","parentId":81714,"sort":0,"initial":"H"},{"id":89828,"name":"\u9ec4\u5c71","type":2,"path":"3410","parentId":81714,"sort":0,"initial":"H"},{"id":576185,"name":"\u83cf\u6cfd","type":2,"path":"3717","parentId":493130,"sort":0,"initial":"H"},{"id":253298,"name":"\u9e64\u58c1","type":2,"path":"4106","parentId":237641,"sort":0,"initial":"H"},{"id":311356,"name":"\u9ec4\u77f3","type":2,"path":"4202","parentId":307715,"sort":0,"initial":"H"},{"id":327798,"name":"\u9ec4\u5188","type":2,"path":"4211","parentId":307715,"sort":0,"initial":"H"},{"id":345952,"name":"\u8861\u9633","type":2,"path":"4304","parentId":339656,"sort":0,"initial":"H"},{"id":380758,"name":"\u6000\u5316","type":2,"path":"4312","parentId":339656,"sort":0,"initial":"H"},{"id":122170,"name":"\u60e0\u5dde","type":2,"path":"4413","parentId":107712,"sort":0,"initial":"H"},{"id":126854,"name":"\u6cb3\u6e90","type":2,"path":"4416","parentId":107712,"sort":0,"initial":"H"},{"id":148546,"name":"\u8d3a\u5dde","type":2,"path":"4511","parentId":135425,"sort":0,"initial":"H"},{"id":149378,"name":"\u6cb3\u6c60","type":2,"path":"4512","parentId":135425,"sort":0,"initial":"H"},{"id":175821,"name":"\u6d77\u53e3","type":2,"path":"4601","parentId":175820,"sort":0,"initial":"H"},{"id":749624,"name":"\u7ea2\u6cb3\u5dde","type":2,"path":"5325","parentId":739032,"sort":0,"initial":"H"},{"id":631214,"name":"\u6c49\u4e2d","type":2,"path":"6107","parentId":613964,"sort":0,"initial":"H"},{"id":489297,"name":"\u6d77\u4e1c","type":2,"path":"6321","parentId":488119,"sort":0,"initial":"H"},{"id":491034,"name":"\u6d77\u5317\u5dde","type":2,"path":"6322","parentId":488119,"sort":0,"initial":"H"},{"id":491321,"name":"\u9ec4\u5357\u5dde","type":2,"path":"6323","parentId":488119,"sort":0,"initial":"H"},{"id":491626,"name":"\u6d77\u5357\u5dde","type":2,"path":"6325","parentId":488119,"sort":0,"initial":"H"},{"id":492709,"name":"\u6d77\u897f\u5dde","type":2,"path":"6328","parentId":488119,"sort":0,"initial":"H"},{"id":724652,"name":"\u54c8\u5bc6","type":2,"path":"6522","parentId":723476,"sort":0,"initial":"H"},{"id":732988,"name":"\u548c\u7530","type":2,"path":"6532","parentId":723476,"sort":0,"initial":"H"}],"J":[{"id":591287,"name":"\u664b\u57ce","type":2,"path":"1405","parentId":582414,"sort":0,"initial":"J"},{"id":595591,"name":"\u664b\u4e2d","type":2,"path":"1407","parentId":582414,"sort":0,"initial":"J"},{"id":459625,"name":"\u9526\u5dde","type":2,"path":"2107","parentId":451186,"sort":0,"initial":"J"},{"id":393450,"name":"\u5409\u6797","type":2,"path":"2202","parentId":391143,"sort":0,"initial":"J"},{"id":296807,"name":"\u9e21\u897f","type":2,"path":"2303","parentId":291426,"sort":0,"initial":"J"},{"id":300907,"name":"\u4f73\u6728\u65af","type":2,"path":"2308","parentId":291426,"sort":0,"initial":"J"},{"id":31894,"name":"\u5609\u5174","type":2,"path":"3304","parentId":18047,"sort":0,"initial":"J"},{"id":38035,"name":"\u91d1\u534e","type":2,"path":"3307","parentId":18047,"sort":0,"initial":"J"},{"id":430763,"name":"\u666f\u5fb7\u9547","type":2,"path":"3602","parentId":428836,"sort":0,"initial":"J"},{"id":432398,"name":"\u4e5d\u6c5f","type":2,"path":"3604","parentId":428836,"sort":0,"initial":"J"},{"id":440045,"name":"\u5409\u5b89","type":2,"path":"3608","parentId":428836,"sort":0,"initial":"J"},{"id":493131,"name":"\u6d4e\u5357","type":2,"path":"3701","parentId":493130,"sort":0,"initial":"J"},{"id":530139,"name":"\u6d4e\u5b81","type":2,"path":"3708","parentId":493130,"sort":0,"initial":"J"},{"id":258171,"name":"\u7126\u4f5c","type":2,"path":"4108","parentId":237641,"sort":0,"initial":"J"},{"id":319597,"name":"\u8346\u95e8","type":2,"path":"4208","parentId":307715,"sort":0,"initial":"J"},{"id":324609,"name":"\u8346\u5dde","type":2,"path":"4210","parentId":307715,"sort":0,"initial":"J"},{"id":115077,"name":"\u6c5f\u95e8","type":2,"path":"4407","parentId":107712,"sort":0,"initial":"J"},{"id":132632,"name":"\u63ed\u9633","type":2,"path":"4452","parentId":107712,"sort":0,"initial":"J"},{"id":57113,"name":"\u5609\u5cea\u5173","type":2,"path":"6202","parentId":55845,"sort":0,"initial":"J"},{"id":57188,"name":"\u91d1\u660c","type":2,"path":"6203","parentId":55845,"sort":0,"initial":"J"},{"id":65157,"name":"\u9152\u6cc9","type":2,"path":"6209","parentId":55845,"sort":0,"initial":"J"}],"K":[{"id":240649,"name":"\u5f00\u5c01","type":2,"path":"4102","parentId":237641,"sort":0,"initial":"K"},{"id":739033,"name":"\u6606\u660e","type":2,"path":"5301","parentId":739032,"sort":0,"initial":"K"},{"id":724220,"name":"\u514b\u62c9\u739b\u4f9d","type":2,"path":"6502","parentId":723476,"sort":0,"initial":"K"},{"id":729754,"name":"\u514b\u5dde","type":2,"path":"6530","parentId":723476,"sort":0,"initial":"K"},{"id":730130,"name":"\u5580\u4ec0","type":2,"path":"6531","parentId":723476,"sort":0,"initial":"K"}],"L":[{"id":228914,"name":"\u5eca\u574a","type":2,"path":"1310","parentId":182754,"sort":0,"initial":"L"},{"id":607277,"name":"\u4e34\u6c7e","type":2,"path":"1410","parentId":582414,"sort":0,"initial":"L"},{"id":610589,"name":"\u5415\u6881","type":2,"path":"1411","parentId":582414,"sort":0,"initial":"L"},{"id":462997,"name":"\u8fbd\u9633","type":2,"path":"2110","parentId":451186,"sort":0,"initial":"L"},{"id":396899,"name":"\u8fbd\u6e90","type":2,"path":"2204","parentId":391143,"sort":0,"initial":"L"},{"id":416015,"name":"\u8fde\u4e91\u6e2f","type":2,"path":"3207","parentId":403889,"sort":0,"initial":"L"},{"id":52064,"name":"\u4e3d\u6c34","type":2,"path":"3311","parentId":18047,"sort":0,"initial":"L"},{"id":100497,"name":"\u516d\u5b89","type":2,"path":"3415","parentId":81714,"sort":0,"initial":"L"},{"id":13562,"name":"\u9f99\u5ca9","type":2,"path":"3508","parentId":2,"sort":0,"initial":"L"},{"id":546757,"name":"\u83b1\u829c","type":2,"path":"3712","parentId":493130,"sort":0,"initial":"L"},{"id":547853,"name":"\u4e34\u6c82","type":2,"path":"3713","parentId":493130,"sort":0,"initial":"L"},{"id":564076,"name":"\u804a\u57ce","type":2,"path":"3715","parentId":493130,"sort":0,"initial":"L"},{"id":243298,"name":"\u6d1b\u9633","type":2,"path":"4103","parentId":237641,"sort":0,"initial":"L"},{"id":385214,"name":"\u5a04\u5e95","type":2,"path":"4313","parentId":339656,"sort":0,"initial":"L"},{"id":137369,"name":"\u67f3\u5dde","type":2,"path":"4502","parentId":135425,"sort":0,"initial":"L"},{"id":151173,"name":"\u6765\u5bbe","type":2,"path":"4513","parentId":135425,"sort":0,"initial":"L"},{"id":673404,"name":"\u4e50\u5c71","type":2,"path":"5111","parentId":650698,"sort":0,"initial":"L"},{"id":706605,"name":"\u51c9\u5c71\u5dde","type":2,"path":"5134","parentId":650698,"sort":0,"initial":"L"},{"id":154692,"name":"\u516d\u76d8\u6c34","type":2,"path":"5202","parentId":152964,"sort":0,"initial":"L"},{"id":745693,"name":"\u4e3d\u6c5f","type":2,"path":"5307","parentId":739032,"sort":0,"initial":"L"},{"id":747377,"name":"\u4e34\u6ca7","type":2,"path":"5309","parentId":739032,"sort":0,"initial":"L"},{"id":716799,"name":"\u62c9\u8428","type":2,"path":"5401","parentId":716798,"sort":0,"initial":"L"},{"id":722882,"name":"\u6797\u829d","type":2,"path":"5426","parentId":716798,"sort":0,"initial":"L"},{"id":55846,"name":"\u5170\u5dde","type":2,"path":"6201","parentId":55845,"sort":0,"initial":"L"},{"id":69209,"name":"\u9647\u5357","type":2,"path":"6212","parentId":55845,"sort":0,"initial":"L"},{"id":72730,"name":"\u4e34\u590f\u5dde","type":2,"path":"6229","parentId":55845,"sort":0,"initial":"L"}],"M":[{"id":302887,"name":"\u7261\u4e39\u6c5f","type":2,"path":"2310","parentId":291426,"sort":0,"initial":"M"},{"id":86235,"name":"\u9a6c\u978d\u5c71","type":2,"path":"3405","parentId":81714,"sort":0,"initial":"M"},{"id":118472,"name":"\u8302\u540d","type":2,"path":"4409","parentId":107712,"sort":0,"initial":"M"},{"id":123530,"name":"\u6885\u5dde","type":2,"path":"4414","parentId":107712,"sort":0,"initial":"M"},{"id":661421,"name":"\u7ef5\u9633","type":2,"path":"5107","parentId":650698,"sort":0,"initial":"M"},{"id":682226,"name":"\u7709\u5c71","type":2,"path":"5114","parentId":650698,"sort":0,"initial":"M"}],"N":[{"id":403890,"name":"\u5357\u4eac","type":2,"path":"3201","parentId":403889,"sort":0,"initial":"N"},{"id":413570,"name":"\u5357\u901a","type":2,"path":"3206","parentId":403889,"sort":0,"initial":"N"},{"id":22636,"name":"\u5b81\u6ce2","type":2,"path":"3302","parentId":18047,"sort":0,"initial":"N"},{"id":11533,"name":"\u5357\u5e73","type":2,"path":"3507","parentId":2,"sort":0,"initial":"N"},{"id":15608,"name":"\u5b81\u5fb7\u3000","type":2,"path":"3509","parentId":2,"sort":0,"initial":"N"},{"id":428837,"name":"\u5357\u660c","type":2,"path":"3601","parentId":428836,"sort":0,"initial":"N"},{"id":269442,"name":"\u5357\u9633","type":2,"path":"4113","parentId":237641,"sort":0,"initial":"N"},{"id":135426,"name":"\u5357\u5b81","type":2,"path":"4501","parentId":135425,"sort":0,"initial":"N"},{"id":670954,"name":"\u5185\u6c5f","type":2,"path":"5110","parentId":650698,"sort":0,"initial":"N"},{"id":676108,"name":"\u5357\u5145","type":2,"path":"5113","parentId":650698,"sort":0,"initial":"N"},{"id":754163,"name":"\u6012\u6c5f\u5dde","type":2,"path":"5333","parentId":739032,"sort":0,"initial":"N"},{"id":721282,"name":"\u90a3\u66f2","type":2,"path":"5424","parentId":716798,"sort":0,"initial":"N"}],"O":[],"P":[{"id":463726,"name":"\u76d8\u9526","type":2,"path":"2111","parentId":451186,"sort":0,"initial":"P"},{"id":3631,"name":"\u8386\u7530","type":2,"path":"3503","parentId":2,"sort":0,"initial":"P"},{"id":431560,"name":"\u840d\u4e61","type":2,"path":"3603","parentId":428836,"sort":0,"initial":"P"},{"id":246751,"name":"\u5e73\u9876\u5c71","type":2,"path":"4104","parentId":237641,"sort":0,"initial":"P"},{"id":656346,"name":"\u6500\u679d\u82b1","type":2,"path":"5104","parentId":650698,"sort":0,"initial":"P"},{"id":63447,"name":"\u5e73\u51c9","type":2,"path":"6208","parentId":55845,"sort":0,"initial":"P"}],"Q":[{"id":193972,"name":"\u79e6\u7687\u5c9b","type":2,"path":"1303","parentId":182754,"sort":0,"initial":"Q"},{"id":294766,"name":"\u9f50\u9f50\u54c8\u5c14","type":2,"path":"2302","parentId":291426,"sort":0,"initial":"Q"},{"id":302482,"name":"\u4e03\u53f0\u6cb3","type":2,"path":"2309","parentId":291426,"sort":0,"initial":"Q"},{"id":6728,"name":"\u6cc9\u5dde","type":2,"path":"3505","parentId":2,"sort":0,"initial":"Q"},{"id":498417,"name":"\u9752\u5c9b","type":2,"path":"3702","parentId":493130,"sort":0,"initial":"Q"},{"id":129281,"name":"\u6e05\u8fdc","type":2,"path":"4418","parentId":107712,"sort":0,"initial":"Q"},{"id":142618,"name":"\u94a6\u5dde","type":2,"path":"4507","parentId":135425,"sort":0,"initial":"Q"},{"id":163200,"name":"\u9ed4\u897f\u5357\u5dde","type":2,"path":"5223","parentId":152964,"sort":0,"initial":"Q"},{"id":169815,"name":"\u9ed4\u4e1c\u5357\u82d7\u65cf\u4f97\u65cf\u81ea\u6cbb\u5dde","type":2,"path":"5226","parentId":152964,"sort":0,"initial":"Q"},{"id":173413,"name":"\u9ed4\u5357\u5e03\u4f9d\u65cf\u82d7\u65cf\u81ea\u6cbb\u5dde","type":2,"path":"5227","parentId":152964,"sort":0,"initial":"Q"},{"id":740775,"name":"\u66f2\u9756","type":2,"path":"5303","parentId":739032,"sort":0,"initial":"Q"},{"id":65773,"name":"\u5e86\u9633","type":2,"path":"6210","parentId":55845,"sort":0,"initial":"Q"}],"R":[{"id":543697,"name":"\u65e5\u7167","type":2,"path":"3711","parentId":493130,"sort":0,"initial":"R"},{"id":719300,"name":"\u65e5\u5580\u5219","type":2,"path":"5423","parentId":716798,"sort":0,"initial":"R"}],"S":[{"id":182755,"name":"\u77f3\u5bb6\u5e84","type":2,"path":"1301","parentId":182754,"sort":0,"initial":"S"},{"id":593715,"name":"\u6714\u5dde","type":2,"path":"1406","parentId":582414,"sort":0,"initial":"S"},{"id":451187,"name":"\u6c88\u9633","type":2,"path":"2101","parentId":451186,"sort":0,"initial":"S"},{"id":395385,"name":"\u56db\u5e73","type":2,"path":"2203","parentId":391143,"sort":0,"initial":"S"},{"id":399649,"name":"\u677e\u539f","type":2,"path":"2207","parentId":391143,"sort":0,"initial":"S"},{"id":298208,"name":"\u53cc\u9e2d\u5c71","type":2,"path":"2305","parentId":291426,"sort":0,"initial":"S"},{"id":305535,"name":"\u7ee5\u5316","type":2,"path":"2312","parentId":291426,"sort":0,"initial":"S"},{"id":645122,"name":"\u4e0a\u6d77","type":2,"path":"3101","parentId":645121,"sort":0,"initial":"S"},{"id":411435,"name":"\u82cf\u5dde","type":2,"path":"3205","parentId":403889,"sort":0,"initial":"S"},{"id":427235,"name":"\u5bbf\u8fc1","type":2,"path":"3213","parentId":403889,"sort":0,"initial":"S"},{"id":34575,"name":"\u7ecd\u5174","type":2,"path":"3306","parentId":18047,"sort":0,"initial":"S"},{"id":96503,"name":"\u5bbf\u5dde","type":2,"path":"3413","parentId":81714,"sort":0,"initial":"S"},{"id":4668,"name":"\u4e09\u660e","type":2,"path":"3504","parentId":2,"sort":0,"initial":"S"},{"id":448209,"name":"\u4e0a\u9976","type":2,"path":"3611","parentId":428836,"sort":0,"initial":"S"},{"id":267887,"name":"\u4e09\u95e8\u5ce1","type":2,"path":"4112","parentId":237641,"sort":0,"initial":"S"},{"id":274594,"name":"\u5546\u4e18","type":2,"path":"4114","parentId":237641,"sort":0,"initial":"S"},{"id":312328,"name":"\u5341\u5830","type":2,"path":"4203","parentId":307715,"sort":0,"initial":"S"},{"id":333702,"name":"\u968f\u5dde","type":2,"path":"4213","parentId":307715,"sort":0,"initial":"S"},{"id":337430,"name":"\u7701\u76f4\u8f96\u884c\u653f\u5355\u4f4d","type":2,"path":"4290","parentId":307715,"sort":0,"initial":"S"},{"id":351593,"name":"\u90b5\u9633","type":2,"path":"4305","parentId":339656,"sort":0,"initial":"S"},{"id":110501,"name":"\u97f6\u5173","type":2,"path":"4402","parentId":107712,"sort":0,"initial":"S"},{"id":112083,"name":"\u6df1\u5733","type":2,"path":"4403","parentId":107712,"sort":0,"initial":"S"},{"id":113125,"name":"\u6c55\u5934","type":2,"path":"4405","parentId":107712,"sort":0,"initial":"S"},{"id":125908,"name":"\u6c55\u5c3e","type":2,"path":"4415","parentId":107712,"sort":0,"initial":"S"},{"id":176381,"name":"\u4e09\u4e9a","type":2,"path":"4602","parentId":175820,"sort":0,"initial":"S"},{"id":176773,"name":"\u7701\u5c5e\u865a\u62df","type":2,"path":"4690","parentId":175820,"sort":0,"initial":"S"},{"id":668542,"name":"\u9042\u5b81","type":2,"path":"5109","parentId":650698,"sort":0,"initial":"S"},{"id":746214,"name":"\u601d\u8305","type":2,"path":"5308","parentId":739032,"sort":0,"initial":"S"},{"id":718610,"name":"\u5c71\u5357","type":2,"path":"5422","parentId":716798,"sort":0,"initial":"S"},{"id":643090,"name":"\u5546\u6d1b","type":2,"path":"6110","parentId":613964,"sort":0,"initial":"S"},{"id":485503,"name":"\u77f3\u5634\u5c71","type":2,"path":"6402","parentId":484915,"sort":0,"initial":"S"},{"id":738443,"name":"\u7701\u76f4\u8f96\u884c\u653f\u5355\u4f4d","type":2,"path":"6590","parentId":723476,"sort":0,"initial":"S"}],"T":[{"id":711070,"name":"\u5929\u6d25","type":2,"path":"1201","parentId":711069,"sort":0,"initial":"T"},{"id":187965,"name":"\u5510\u5c71","type":2,"path":"1302","parentId":182754,"sort":0,"initial":"T"},{"id":582415,"name":"\u592a\u539f","type":2,"path":"1401","parentId":582414,"sort":0,"initial":"T"},{"id":474093,"name":"\u901a\u8fbd","type":2,"path":"1505","parentId":468973,"sort":0,"initial":"T"},{"id":464280,"name":"\u94c1\u5cad","type":2,"path":"2112","parentId":451186,"sort":0,"initial":"T"},{"id":397547,"name":"\u901a\u5316","type":2,"path":"2205","parentId":391143,"sort":0,"initial":"T"},{"id":425168,"name":"\u6cf0\u5dde","type":2,"path":"3212","parentId":403889,"sort":0,"initial":"T"},{"id":46652,"name":"\u53f0\u5dde","type":2,"path":"3310","parentId":18047,"sort":0,"initial":"T"},{"id":87460,"name":"\u94dc\u9675","type":2,"path":"3407","parentId":81714,"sort":0,"initial":"T"},{"id":536887,"name":"\u6cf0\u5b89","type":2,"path":"3709","parentId":493130,"sort":0,"initial":"T"},{"id":160324,"name":"\u94dc\u4ec1","type":2,"path":"5222","parentId":152964,"sort":0,"initial":"T"},{"id":617876,"name":"\u94dc\u5ddd","type":2,"path":"6102","parentId":613964,"sort":0,"initial":"T"},{"id":58262,"name":"\u5929\u6c34","type":2,"path":"6205","parentId":55845,"sort":0,"initial":"T"},{"id":724388,"name":"\u5410\u9c81\u756a","type":2,"path":"6521","parentId":723476,"sort":0,"initial":"T"},{"id":735987,"name":"\u5854\u57ce","type":2,"path":"6542","parentId":723476,"sort":0,"initial":"T"}],"W":[{"id":471458,"name":"\u4e4c\u6d77","type":2,"path":"1503","parentId":468973,"sort":0,"initial":"W"},{"id":480605,"name":"\u4e4c\u5170\u5bdf\u5e03","type":2,"path":"1509","parentId":468973,"sort":0,"initial":"W"},{"id":405615,"name":"\u65e0\u9521","type":2,"path":"3202","parentId":403889,"sort":0,"initial":"W"},{"id":25884,"name":"\u6e29\u5dde","type":2,"path":"3303","parentId":18047,"sort":0,"initial":"W"},{"id":83410,"name":"\u829c\u6e56","type":2,"path":"3402","parentId":81714,"sort":0,"initial":"W"},{"id":520298,"name":"\u6f4d\u574a","type":2,"path":"3707","parentId":493130,"sort":0,"initial":"W"},{"id":540733,"name":"\u5a01\u6d77","type":2,"path":"3710","parentId":493130,"sort":0,"initial":"W"},{"id":307716,"name":"\u6b66\u6c49","type":2,"path":"4201","parentId":307715,"sort":0,"initial":"W"},{"id":140700,"name":"\u68a7\u5dde","type":2,"path":"4504","parentId":135425,"sort":0,"initial":"W"},{"id":751071,"name":"\u6587\u5c71\u5dde","type":2,"path":"5326","parentId":739032,"sort":0,"initial":"W"},{"id":623918,"name":"\u6e2d\u5357","type":2,"path":"6105","parentId":613964,"sort":0,"initial":"W"},{"id":61085,"name":"\u6b66\u5a01","type":2,"path":"6206","parentId":55845,"sort":0,"initial":"W"},{"id":485884,"name":"\u5434\u5fe0","type":2,"path":"6403","parentId":484915,"sort":0,"initial":"W"},{"id":723477,"name":"\u4e4c\u9c81\u6728\u9f50","type":2,"path":"6501","parentId":723476,"sort":0,"initial":"W"}],"X":[{"id":80872,"name":"\u53bf","type":2,"path":"1102","parentId":74873,"sort":0,"initial":"X"},{"id":715034,"name":"\u53bf","type":2,"path":"1202","parentId":711069,"sort":0,"initial":"X"},{"id":202444,"name":"\u90a2\u53f0","type":2,"path":"1305","parentId":182754,"sort":0,"initial":"X"},{"id":602106,"name":"\u5ffb\u5dde","type":2,"path":"1409","parentId":582414,"sort":0,"initial":"X"},{"id":482281,"name":"\u5174\u5b89\u76df","type":2,"path":"1522","parentId":468973,"sort":0,"initial":"X"},{"id":483469,"name":"\u9521\u6797\u90ed\u52d2\u76df","type":2,"path":"1525","parentId":468973,"sort":0,"initial":"X"},{"id":650331,"name":"\u53bf","type":2,"path":"3102","parentId":645121,"sort":0,"initial":"X"},{"id":407074,"name":"\u5f90\u5dde","type":2,"path":"3203","parentId":403889,"sort":0,"initial":"X"},{"id":106680,"name":"\u5ba3\u57ce","type":2,"path":"3418","parentId":81714,"sort":0,"initial":"X"},{"id":3076,"name":"\u53a6\u95e8","type":2,"path":"3502","parentId":2,"sort":0,"initial":"X"},{"id":434871,"name":"\u65b0\u4f59","type":2,"path":"3605","parentId":428836,"sort":0,"initial":"X"},{"id":254296,"name":"\u65b0\u4e61","type":2,"path":"4107","parentId":237641,"sort":0,"initial":"X"},{"id":264000,"name":"\u8bb8\u660c","type":2,"path":"4110","parentId":237641,"sort":0,"initial":"X"},{"id":279630,"name":"\u4fe1\u9633","type":2,"path":"4115","parentId":237641,"sort":0,"initial":"X"},{"id":316350,"name":"\u8944\u6a0a","type":2,"path":"4206","parentId":307715,"sort":0,"initial":"X"},{"id":321323,"name":"\u5b5d\u611f","type":2,"path":"4209","parentId":307715,"sort":0,"initial":"X"},{"id":332446,"name":"\u54b8\u5b81","type":2,"path":"4212","parentId":307715,"sort":0,"initial":"X"},{"id":343985,"name":"\u6e58\u6f6d","type":2,"path":"4303","parentId":339656,"sort":0,"initial":"X"},{"id":388832,"name":"\u6e58\u897f\u571f\u5bb6\u65cf\u82d7\u65cf\u81ea\u6cbb\u5dde","type":2,"path":"4331","parentId":339656,"sort":0,"initial":"X"},{"id":752142,"name":"\u897f\u53cc\u7248\u7eb3\u5dde","type":2,"path":"5328","parentId":739032,"sort":0,"initial":"X"},{"id":613965,"name":"\u897f\u5b89","type":2,"path":"6101","parentId":613964,"sort":0,"initial":"X"},{"id":620668,"name":"\u54b8\u9633","type":2,"path":"6104","parentId":613964,"sort":0,"initial":"X"},{"id":488120,"name":"\u897f\u5b81","type":2,"path":"6301","parentId":488119,"sort":0,"initial":"X"}],"Y":[{"id":586426,"name":"\u9633\u6cc9","type":2,"path":"1403","parentId":582414,"sort":0,"initial":"Y"},{"id":598639,"name":"\u8fd0\u57ce","type":2,"path":"1408","parentId":582414,"sort":0,"initial":"Y"},{"id":461146,"name":"\u8425\u53e3","type":2,"path":"2108","parentId":451186,"sort":0,"initial":"Y"},{"id":402247,"name":"\u5ef6\u8fb9\u671d\u9c9c\u65cf\u81ea\u6cbb\u5dde","type":2,"path":"2224","parentId":391143,"sort":0,"initial":"Y"},{"id":299997,"name":"\u4f0a\u6625","type":2,"path":"2307","parentId":291426,"sort":0,"initial":"Y"},{"id":419692,"name":"\u76d0\u57ce","type":2,"path":"3209","parentId":403889,"sort":0,"initial":"Y"},{"id":422449,"name":"\u626c\u5dde","type":2,"path":"3210","parentId":403889,"sort":0,"initial":"Y"},{"id":435382,"name":"\u9e70\u6f6d","type":2,"path":"3606","parentId":428836,"sort":0,"initial":"Y"},{"id":443122,"name":"\u5b9c\u6625","type":2,"path":"3609","parentId":428836,"sort":0,"initial":"Y"},{"id":513384,"name":"\u70df\u53f0","type":2,"path":"3706","parentId":493130,"sort":0,"initial":"Y"},{"id":314530,"name":"\u5b9c\u660c","type":2,"path":"4205","parentId":307715,"sort":0,"initial":"Y"},{"id":357788,"name":"\u5cb3\u9633","type":2,"path":"4306","parentId":339656,"sort":0,"initial":"Y"},{"id":367799,"name":"\u76ca\u9633","type":2,"path":"4309","parentId":339656,"sort":0,"initial":"Y"},{"id":375137,"name":"\u6c38\u5dde","type":2,"path":"4311","parentId":339656,"sort":0,"initial":"Y"},{"id":128373,"name":"\u9633\u6c5f","type":2,"path":"4417","parentId":107712,"sort":0,"initial":"Y"},{"id":134374,"name":"\u4e91\u6d6e","type":2,"path":"4453","parentId":107712,"sort":0,"initial":"Y"},{"id":144949,"name":"\u7389\u6797","type":2,"path":"4509","parentId":135425,"sort":0,"initial":"Y"},{"id":684831,"name":"\u5b9c\u5bbe","type":2,"path":"5115","parentId":650698,"sort":0,"initial":"Y"},{"id":694865,"name":"\u96c5\u5b89","type":2,"path":"5118","parentId":650698,"sort":0,"initial":"Y"},{"id":742502,"name":"\u7389\u6eaa","type":2,"path":"5304","parentId":739032,"sort":0,"initial":"Y"},{"id":627544,"name":"\u5ef6\u5b89","type":2,"path":"6106","parentId":613964,"sort":0,"initial":"Y"},{"id":634429,"name":"\u6986\u6797","type":2,"path":"6108","parentId":613964,"sort":0,"initial":"Y"},{"id":492383,"name":"\u7389\u6811\u5dde","type":2,"path":"6327","parentId":488119,"sort":0,"initial":"Y"},{"id":484916,"name":"\u94f6\u5ddd","type":2,"path":"6401","parentId":484915,"sort":0,"initial":"Y"},{"id":734603,"name":"\u4f0a\u7281\u5dde","type":2,"path":"6540","parentId":723476,"sort":0,"initial":"Y"}],"Z":[{"id":214981,"name":"\u5f20\u5bb6\u53e3","type":2,"path":"1307","parentId":182754,"sort":0,"initial":"Z"},{"id":424112,"name":"\u9547\u6c5f","type":2,"path":"3211","parentId":403889,"sort":0,"initial":"Z"},{"id":43349,"name":"\u8862\u5dde","type":2,"path":"3308","parentId":18047,"sort":0,"initial":"Z"},{"id":46108,"name":"\u821f\u5c71","type":2,"path":"3309","parentId":18047,"sort":0,"initial":"Z"},{"id":103717,"name":"\u4eb3\u5dde","type":2,"path":"3416","parentId":81714,"sort":0,"initial":"Z"},{"id":9403,"name":"\u6f33\u5dde","type":2,"path":"3506","parentId":2,"sort":0,"initial":"Z"},{"id":505283,"name":"\u6dc4\u535a","type":2,"path":"3703","parentId":493130,"sort":0,"initial":"Z"},{"id":508941,"name":"\u67a3\u5e84","type":2,"path":"3704","parentId":493130,"sort":0,"initial":"Z"},{"id":237642,"name":"\u90d1\u5dde","type":2,"path":"4101","parentId":237641,"sort":0,"initial":"Z"},{"id":260814,"name":"\u6fee\u9633","type":2,"path":"4109","parentId":237641,"sort":0,"initial":"Z"},{"id":266517,"name":"\u6f2f\u6cb3","type":2,"path":"4111","parentId":237641,"sort":0,"initial":"Z"},{"id":283179,"name":"\u5468\u53e3","type":2,"path":"4116","parentId":237641,"sort":0,"initial":"Z"},{"id":288419,"name":"\u9a7b\u9a6c\u5e97","type":2,"path":"4117","parentId":237641,"sort":0,"initial":"Z"},{"id":341672,"name":"\u682a\u6d32","type":2,"path":"4302","parentId":339656,"sort":0,"initial":"Z"},{"id":366030,"name":"\u5f20\u5bb6\u754c","type":2,"path":"4308","parentId":339656,"sort":0,"initial":"Z"},{"id":112797,"name":"\u73e0\u6d77","type":2,"path":"4404","parentId":107712,"sort":0,"initial":"Z"},{"id":116502,"name":"\u6e5b\u6c5f","type":2,"path":"4408","parentId":107712,"sort":0,"initial":"Z"},{"id":120491,"name":"\u8087\u5e86","type":2,"path":"4412","parentId":107712,"sort":0,"initial":"Z"},{"id":131230,"name":"\u4e2d\u5c71","type":2,"path":"4420","parentId":107712,"sort":0,"initial":"Z"},{"id":654512,"name":"\u81ea\u8d21","type":2,"path":"5103","parentId":650698,"sort":0,"initial":"Z"},{"id":656896,"name":"\u6cf8\u5dde","type":2,"path":"5105","parentId":650698,"sort":0,"initial":"Z"},{"id":698940,"name":"\u8d44\u9633","type":2,"path":"5120","parentId":650698,"sort":0,"initial":"Z"},{"id":156033,"name":"\u9075\u4e49","type":2,"path":"5203","parentId":152964,"sort":0,"initial":"Z"},{"id":744263,"name":"\u662d\u901a","type":2,"path":"5306","parentId":739032,"sort":0,"initial":"Z"},{"id":62415,"name":"\u5f20\u6396","type":2,"path":"6207","parentId":55845,"sort":0,"initial":"Z"},{"id":487595,"name":"\u4e2d\u536b","type":2,"path":"6405","parentId":484915,"sort":0,"initial":"Z"}]},"info":"\u83b7\u53d6\u6210\u529f"}